{
  "breakpoints": {
    "375": {
      "name": "inventory-table",
      "viewportWidth": 293,
      "width": 293,
      "height": 418,
      "bones": [
        [
          0,
          0,
          100,
          74,
          16,
          true
        ],
        [
          5.802,
          17,
          13.6519,
          40,
          12
        ],
        [
          23.5495,
          19,
          43.686,
          16,
          4
        ],
        [
          23.5495,
          43,
          27.3038,
          12,
          4
        ],
        [
          77.8157,
          27,
          16.3823,
          20,
          4
        ],
        [
          0,
          86,
          100,
          74,
          16,
          true
        ],
        [
          5.802,
          103,
          13.6519,
          40,
          12
        ],
        [
          23.5495,
          105,
          43.686,
          16,
          4
        ],
        [
          23.5495,
          129,
          27.3038,
          12,
          4
        ],
        [
          77.8157,
          113,
          16.3823,
          20,
          4
        ],
        [
          0,
          172,
          100,
          74,
          16,
          true
        ],
        [
          5.802,
          189,
          13.6519,
          40,
          12
        ],
        [
          23.5495,
          191,
          43.686,
          16,
          4
        ],
        [
          23.5495,
          215,
          27.3038,
          12,
          4
        ],
        [
          77.8157,
          199,
          16.3823,
          20,
          4
        ],
        [
          0,
          258,
          100,
          74,
          16,
          true
        ],
        [
          5.802,
          275,
          13.6519,
          40,
          12
        ],
        [
          23.5495,
          277,
          43.686,
          16,
          4
        ],
        [
          23.5495,
          301,
          27.3038,
          12,
          4
        ],
        [
          77.8157,
          285,
          16.3823,
          20,
          4
        ],
        [
          0,
          344,
          100,
          74,
          16,
          true
        ],
        [
          5.802,
          361,
          13.6519,
          40,
          12
        ],
        [
          23.5495,
          363,
          43.686,
          16,
          4
        ],
        [
          23.5495,
          387,
          27.3038,
          12,
          4
        ],
        [
          77.8157,
          371,
          16.3823,
          20,
          4
        ]
      ]
    },
    "640": {
      "name": "inventory-table",
      "viewportWidth": 0,
      "width": 0,
      "height": 0,
      "bones": []
    },
    "768": {
      "name": "inventory-table",
      "viewportWidth": 0,
      "width": 0,
      "height": 0,
      "bones": []
    },
    "1024": {
      "name": "inventory-table",
      "viewportWidth": 0,
      "width": 0,
      "height": 0,
      "bones": []
    },
    "1280": {
      "name": "inventory-table",
      "viewportWidth": 0,
      "width": 0,
      "height": 0,
      "bones": []
    },
    "1536": {
      "name": "inventory-table",
      "viewportWidth": 0,
      "width": 0,
      "height": 0,
      "bones": []
    }
  },
  "_hash": "204d4c68b965b311cba7bc997639533f"
}